libraccoon/__init__.py
libraccoon/main.py
libraccoon/libs/__init__.py
libraccoon/libs/bingip2host.py
libraccoon/libs/corscanner.py
libraccoon/libs/dns_handler.py
libraccoon/libs/fierce.py
libraccoon/libs/fuzzer.py
libraccoon/libs/host.py
libraccoon/libs/knockpy.py
libraccoon/libs/scanless.py
libraccoon/libs/storage_explorer.py
libraccoon/libs/sub_domain.py
libraccoon/libs/subbrute.py
libraccoon/libs/subdomainizer.py
libraccoon/libs/waf.py
libraccoon/libs/web_app.py
libraccoon/libs/whatwebapi.py
libraccoon/utils/__init__.py
libraccoon/utils/exceptions.py
libraccoon/utils/help_utils.py
libraccoon/utils/request_handler.py
libraccoon/utils/singleton.py
libraccoon/utils/utils.py
libraccoon/utils/web_server_validator.py
libraccoon/wordlists/__init__.py
libraccoon/wordlists/nmap-services.txt
libraccoon/wordlists/wordlist_helper.py
python3_libraccoon-3.3.6.dist-info/licenses/LICENSE
python3_libraccoon-3.3.6.dist-info/METADATA
python3_libraccoon-3.3.6.dist-info/WHEEL
python3_libraccoon-3.3.6.dist-info/top_level.txt
python3_libraccoon-3.3.6.dist-info/RECORD
