Metadata-Version: 2.4
Name: python3-libraccoon
Version: 3.3.6
Summary: libraccon a library for high performance offensive security tool for reconnaissance based on raccoon scanner. This include performing DNS reconnaissance
Author-email: nmmapper <inquiry@nmmapper.com>
Project-URL: Homepage, https://github.com/nmmapper/python3-libraccoon
Classifier: Programming Language :: Python :: 3
Classifier: Programming Language :: Python :: 3.11
Classifier: Programming Language :: Python :: 3.12
Classifier: Programming Language :: Python :: 3.13
Classifier: License :: OSI Approved :: GNU General Public License v2 (GPLv2)
Classifier: Operating System :: OS Independent
Requires-Python: >=3.11
License-File: LICENSE
Requires-Dist: aiodns
Requires-Dist: aiofiles
Requires-Dist: python-whois
Requires-Dist: httpx
Requires-Dist: bs4
Requires-Dist: dnspython
Requires-Dist: requests
Requires-Dist: ipaddress
Requires-Dist: xmltodict
Requires-Dist: geoip2
Requires-Dist: httpx
Requires-Dist: tld
Requires-Dist: simplejson
Dynamic: license-file
